application_kit_hxrn/__init__.py
application_kit_hxrn/application.py
application_kit_hxrn/logging.py
application_kit_hxrn/process.py
application_kit_hxrn/profiler.py
application_kit_hxrn-0.1.1.dist-info/LICENSE.md
application_kit_hxrn-0.1.1.dist-info/WHEEL
application_kit_hxrn-0.1.1.dist-info/METADATA
application_kit_hxrn-0.1.1.dist-info/RECORD
