Metadata-Version: 2.1
Name: application-kit-hxrn
Version: 0.1.1
Summary: 
License: MIT
Author: hexrain
Author-email: hexrain@yandex.ru
Requires-Python: >=3.9,<4.0
Classifier: License :: OSI Approved :: MIT License
Classifier: Programming Language :: Python :: 3
Classifier: Programming Language :: Python :: 3.9
Requires-Dist: PyYAML (==5.3.1)
Requires-Dist: aiohttp (>=3.7.4,<4.0.0)
Requires-Dist: python-dotenv (==0.13.0)
